README.rst
setup.py
spill/__init__.py
spill.egg-info/PKG-INFO
spill.egg-info/SOURCES.txt
spill.egg-info/dependency_links.txt
spill.egg-info/entry_points.txt
spill.egg-info/requires.txt
spill.egg-info/top_level.txt