Metadata-Version: 1.1
Name: spill
Version: 0.0.1a0
Summary: A utility for generating Flask scaffolding and boilerplate.
Home-page: https://github.com/hawk-sf/spill
Author: James Hawkins
Author-email: jameshawkins.sf@gmail.com
License: MIT
Keywords: Flask web development
Platform: UNKNOWN
Classifier: Development Status :: 3 - Alpha
Classifier: Intended Audience :: Developers
Classifier: Framework :: Flask
Classifier: Programming Language :: Python :: 2
Classifier: Programming Language :: Python :: 2.7
